sypivlib/__init__.py
sypivlib/function/__init__.py
sypivlib/function/dataio.py
sypivlib/function/integration.py
sypivlib/function/interpolation.py
sypivlib/function/search.py
sypivlib/function/variables.py
sypivlib/sypiv/__init__.py
sypivlib/sypiv/ccd_projection.py
sypivlib/sypiv/create_particles.py
sypivlib/sypiv/image_gen.py
sypivlib/sypiv/intensity.py
sypivlib-0.0.1a7.dist-info/LICENSE
sypivlib-0.0.1a7.dist-info/METADATA
sypivlib-0.0.1a7.dist-info/WHEEL
sypivlib-0.0.1a7.dist-info/top_level.txt
sypivlib-0.0.1a7.dist-info/RECORD
