Metadata-Version: 2.1
Name: sypivlib
Version: 0.0.1a7
Summary: Code to generate synthetic PIV images.
Author: Dilip Kalagotla
Author-email: dilipkalagotla@gmail.com
Project-URL: homepage, https://github.com/kalagotla/syPIV
Project-URL: issues, https://github.com/kalagotla/syPIV/issues
Classifier: Programming Language :: Python :: 3
Classifier: Programming Language :: Python :: 3.10
Classifier: Programming Language :: Python :: 3.11
Classifier: Programming Language :: Python :: 3.12
Classifier: License :: OSI Approved :: MIT License
Classifier: Operating System :: OS Independent
Classifier: Intended Audience :: Science/Research
Classifier: Intended Audience :: Education
Classifier: Topic :: Scientific/Engineering
Requires-Python: >=3.10
License-File: LICENSE
Requires-Dist: numpy
Requires-Dist: scipy
Requires-Dist: matplotlib
Requires-Dist: pandas
Requires-Dist: seaborn
Requires-Dist: tqdm
Requires-Dist: mpi4py
Requires-Dist: scikit-learn
Requires-Dist: dask
Requires-Dist: numba
